miro_dbt_linter/__init__.py
miro_dbt_linter/__main__.py
miro_dbt_linter/cli.py
miro_dbt_linter/linter.py
miro_dbt_linter/models.py
miro_dbt_linter/rules.py
miro_dbt_linter/settings.py
miro_dbt_linter/version.py
miro_dbt_linter-0.0.1.dist-info/METADATA
miro_dbt_linter-0.0.1.dist-info/WHEEL
miro_dbt_linter-0.0.1.dist-info/entry_points.txt
miro_dbt_linter-0.0.1.dist-info/top_level.txt
miro_dbt_linter-0.0.1.dist-info/RECORD
