Metadata-Version: 2.1
Name: miro-dbt-linter
Version: 0.0.1
Summary: Extensible linter for dbt projects.
Home-page: https://github.com/tjwaterman99/miro-dbt-linter
Author: Tom Waterman
Author-email: tjwaterman99@gmail.com
License: UNKNOWN
Platform: UNKNOWN
Requires-Dist: pydantic (==1.8.2)
Requires-Dist: rich (==10.9.0)
